{
    "orders": [
        {
            "item": "default",
            "quantity": 0,
            "price": 0,
            "buyer": "NoName",
            "date": "2023-04-08"
        },
        {
            "item": "default",
            "quantity": 0,
            "price": 0,
            "buyer": "NoName",
            "date": "2023-04-08"
        },
        {
            "item": "default",
            "quantity": 0,
            "price": 0,
            "buyer": "NoName",
            "date": "2023-04-08"
        }
    ]
}